{
  "_note": "Accumulated daily Open-Meteo actuals for indonesia regions. Grows daily; never overwrites past days with gaps.",
  "regions": {
    "Lampung": {
      "2026-02-20": {
        "rain": 0.0,
        "tmean": null
      },
      "2026-02-21": {
        "rain": 0.0,
        "tmean": null
      },
      "2026-02-22": {
        "rain": 0.0,
        "tmean": null
      },
      "2026-02-23": {
        "rain": 0.0,
        "tmean": null
      },
      "2026-02-24": {
        "rain": 0.0,
        "tmean": null
      },
      "2026-02-25": {
        "rain": 0.0,
        "tmean": null
      },
      "2026-02-26": {
        "rain": 0.0,
        "tmean": null
      },
      "2026-02-27": {
        "rain": 0.0,
        "tmean": null
      },
      "2026-02-28": {
        "rain": 0.0,
        "tmean": null
      },
      "2026-03-01": {
        "rain": 0.0,
        "tmean": null
      },
      "2026-03-02": {
        "rain": 0.0,
        "tmean": null
      },
      "2026-03-03": {
        "rain": 0.0,
        "tmean": null
      },
      "2026-03-04": {
        "rain": 0.0,
        "tmean": null
      },
      "2026-03-05": {
        "rain": 0.0,
        "tmean": null
      },
      "2026-03-06": {
        "rain": 0.0,
        "tmean": null
      },
      "2026-03-07": {
        "rain": 0.0,
        "tmean": null
      },
      "2026-03-08": {
        "rain": 0.0,
        "tmean": null
      },
      "2026-03-09": {
        "rain": 0.0,
        "tmean": null
      },
      "2026-03-10": {
        "rain": 0.0,
        "tmean": null
      },
      "2026-03-11": {
        "rain": 57.7,
        "tmean": 26.0
      },
      "2026-03-12": {
        "rain": 28.2,
        "tmean": 25.5
      },
      "2026-03-13": {
        "rain": 13.4,
        "tmean": 26.0
      },
      "2026-03-14": {
        "rain": 5.5,
        "tmean": 26.4
      },
      "2026-03-15": {
        "rain": 7.4,
        "tmean": 26.2
      },
      "2026-03-16": {
        "rain": 7.2,
        "tmean": 26.4
      },
      "2026-03-17": {
        "rain": 21.4,
        "tmean": 26.0
      },
      "2026-03-18": {
        "rain": 19.0,
        "tmean": 26.2
      },
      "2026-03-19": {
        "rain": 9.4,
        "tmean": 26.6
      },
      "2026-03-20": {
        "rain": 11.2,
        "tmean": 26.9
      },
      "2026-03-21": {
        "rain": 13.7,
        "tmean": 26.3
      },
      "2026-03-22": {
        "rain": 6.8,
        "tmean": 26.4
      },
      "2026-03-23": {
        "rain": 7.1,
        "tmean": 25.3
      },
      "2026-03-24": {
        "rain": 1.5,
        "tmean": 24.7
      },
      "2026-03-25": {
        "rain": 18.1,
        "tmean": 24.2
      },
      "2026-03-26": {
        "rain": 7.5,
        "tmean": 26.1
      },
      "2026-03-27": {
        "rain": 12.0,
        "tmean": 27.0
      },
      "2026-03-28": {
        "rain": 11.0,
        "tmean": 26.0
      },
      "2026-03-29": {
        "rain": 7.7,
        "tmean": 26.7
      },
      "2026-03-30": {
        "rain": 19.0,
        "tmean": 26.3
      },
      "2026-03-31": {
        "rain": 18.3,
        "tmean": 26.4
      },
      "2026-04-01": {
        "rain": 3.3,
        "tmean": 26.7
      },
      "2026-04-02": {
        "rain": 7.5,
        "tmean": 27.4
      },
      "2026-04-03": {
        "rain": 20.5,
        "tmean": 27.3
      },
      "2026-04-04": {
        "rain": 16.0,
        "tmean": 26.9
      },
      "2026-04-05": {
        "rain": 3.3,
        "tmean": 26.4
      },
      "2026-04-06": {
        "rain": 5.6,
        "tmean": 27.0
      },
      "2026-04-07": {
        "rain": 3.8,
        "tmean": 27.5
      },
      "2026-04-08": {
        "rain": 8.3,
        "tmean": 26.9
      },
      "2026-04-09": {
        "rain": 1.0,
        "tmean": 27.8
      },
      "2026-04-10": {
        "rain": 12.6,
        "tmean": 27.4
      },
      "2026-04-11": {
        "rain": 18.2,
        "tmean": 27.0
      },
      "2026-04-12": {
        "rain": 1.0,
        "tmean": 27.1
      },
      "2026-04-13": {
        "rain": 2.9,
        "tmean": 27.7
      },
      "2026-04-14": {
        "rain": 17.7,
        "tmean": 27.5
      },
      "2026-04-15": {
        "rain": 5.3,
        "tmean": 26.3
      },
      "2026-04-16": {
        "rain": 10.1,
        "tmean": 27.2
      },
      "2026-04-17": {
        "rain": 4.6,
        "tmean": 26.6
      },
      "2026-04-18": {
        "rain": 14.4,
        "tmean": 26.5
      },
      "2026-04-19": {
        "rain": 1.7,
        "tmean": 26.9
      },
      "2026-04-20": {
        "rain": 10.4,
        "tmean": 26.5
      },
      "2026-04-21": {
        "rain": 20.4,
        "tmean": 26.3
      },
      "2026-04-22": {
        "rain": 10.7,
        "tmean": 27.4
      },
      "2026-04-23": {
        "rain": 10.9,
        "tmean": 26.9
      },
      "2026-04-24": {
        "rain": 16.7,
        "tmean": 26.8
      },
      "2026-04-25": {
        "rain": 2.8,
        "tmean": 26.4
      },
      "2026-04-26": {
        "rain": 0.0,
        "tmean": 28.2
      },
      "2026-04-27": {
        "rain": 0.3,
        "tmean": 28.6
      },
      "2026-04-28": {
        "rain": 8.5,
        "tmean": 27.5
      },
      "2026-04-29": {
        "rain": 12.1,
        "tmean": 27.1
      },
      "2026-04-30": {
        "rain": 11.2,
        "tmean": 27.1
      },
      "2026-05-01": {
        "rain": 8.1,
        "tmean": 27.0
      },
      "2026-05-02": {
        "rain": 21.7,
        "tmean": 27.1
      },
      "2026-05-03": {
        "rain": 11.1,
        "tmean": 26.7
      },
      "2026-05-04": {
        "rain": 7.6,
        "tmean": 26.9
      },
      "2026-05-05": {
        "rain": 14.6,
        "tmean": 26.6
      },
      "2026-05-06": {
        "rain": 15.7,
        "tmean": 26.6
      },
      "2026-05-07": {
        "rain": 1.2,
        "tmean": 27.2
      },
      "2026-05-08": {
        "rain": 0.0,
        "tmean": 28.2
      },
      "2026-05-09": {
        "rain": 1.8,
        "tmean": 27.2
      },
      "2026-05-10": {
        "rain": 4.3,
        "tmean": 27.1
      },
      "2026-05-11": {
        "rain": 5.6,
        "tmean": 26.7
      },
      "2026-05-12": {
        "rain": 21.2,
        "tmean": 26.6
      },
      "2026-05-13": {
        "rain": 3.1,
        "tmean": 28.2
      },
      "2026-05-14": {
        "rain": 0.6,
        "tmean": 28.6
      },
      "2026-05-15": {
        "rain": 12.9,
        "tmean": 27.8
      },
      "2026-05-16": {
        "rain": 14.6,
        "tmean": 27.0
      },
      "2026-05-17": {
        "rain": 3.5,
        "tmean": 27.5
      },
      "2026-05-18": {
        "rain": 2.0,
        "tmean": 28.4
      },
      "2026-05-19": {
        "rain": 2.3,
        "tmean": 28.4
      },
      "2026-05-20": {
        "rain": 3.9,
        "tmean": 27.0
      },
      "2026-05-21": {
        "rain": 9.5,
        "tmean": 27.4
      },
      "2026-05-22": {
        "rain": 3.9,
        "tmean": 27.5
      },
      "2026-05-23": {
        "rain": 10.4,
        "tmean": 27.6
      },
      "2026-05-24": {
        "rain": 10.3,
        "tmean": 26.4
      }
    },
    "Gayo": {
      "2026-02-20": {
        "rain": 0.0,
        "tmean": null
      },
      "2026-02-21": {
        "rain": 0.0,
        "tmean": null
      },
      "2026-02-22": {
        "rain": 0.0,
        "tmean": null
      },
      "2026-02-23": {
        "rain": 0.0,
        "tmean": null
      },
      "2026-02-24": {
        "rain": 0.0,
        "tmean": null
      },
      "2026-02-25": {
        "rain": 0.0,
        "tmean": null
      },
      "2026-02-26": {
        "rain": 0.0,
        "tmean": null
      },
      "2026-02-27": {
        "rain": 0.0,
        "tmean": null
      },
      "2026-02-28": {
        "rain": 0.0,
        "tmean": null
      },
      "2026-03-01": {
        "rain": 0.0,
        "tmean": null
      },
      "2026-03-02": {
        "rain": 0.0,
        "tmean": null
      },
      "2026-03-03": {
        "rain": 0.0,
        "tmean": null
      },
      "2026-03-04": {
        "rain": 0.0,
        "tmean": null
      },
      "2026-03-05": {
        "rain": 0.0,
        "tmean": null
      },
      "2026-03-06": {
        "rain": 0.0,
        "tmean": null
      },
      "2026-03-07": {
        "rain": 0.0,
        "tmean": null
      },
      "2026-03-08": {
        "rain": 0.0,
        "tmean": null
      },
      "2026-03-09": {
        "rain": 0.0,
        "tmean": null
      },
      "2026-03-10": {
        "rain": 0.0,
        "tmean": null
      },
      "2026-03-11": {
        "rain": 17.2,
        "tmean": 19.5
      },
      "2026-03-12": {
        "rain": 6.2,
        "tmean": 19.8
      },
      "2026-03-13": {
        "rain": 11.3,
        "tmean": 19.6
      },
      "2026-03-14": {
        "rain": 30.4,
        "tmean": 19.1
      },
      "2026-03-15": {
        "rain": 7.4,
        "tmean": 18.5
      },
      "2026-03-16": {
        "rain": 10.2,
        "tmean": 19.5
      },
      "2026-03-17": {
        "rain": 17.1,
        "tmean": 19.6
      },
      "2026-03-18": {
        "rain": 6.1,
        "tmean": 19.8
      },
      "2026-03-19": {
        "rain": 8.8,
        "tmean": 19.7
      },
      "2026-03-20": {
        "rain": 10.5,
        "tmean": 19.4
      },
      "2026-03-21": {
        "rain": 1.4,
        "tmean": 20.5
      },
      "2026-03-22": {
        "rain": 1.8,
        "tmean": 20.6
      },
      "2026-03-23": {
        "rain": 0.0,
        "tmean": 22.2
      },
      "2026-03-24": {
        "rain": 0.0,
        "tmean": 23.0
      },
      "2026-03-25": {
        "rain": 0.0,
        "tmean": 22.8
      },
      "2026-03-26": {
        "rain": 2.1,
        "tmean": 21.2
      },
      "2026-03-27": {
        "rain": 3.5,
        "tmean": 19.8
      },
      "2026-03-28": {
        "rain": 6.1,
        "tmean": 19.1
      },
      "2026-03-29": {
        "rain": 16.2,
        "tmean": 19.3
      },
      "2026-03-30": {
        "rain": 14.9,
        "tmean": 19.6
      },
      "2026-03-31": {
        "rain": 23.9,
        "tmean": 19.9
      },
      "2026-04-01": {
        "rain": 10.3,
        "tmean": 19.7
      },
      "2026-04-02": {
        "rain": 3.3,
        "tmean": 20.8
      },
      "2026-04-03": {
        "rain": 1.7,
        "tmean": 20.2
      },
      "2026-04-04": {
        "rain": 4.2,
        "tmean": 20.1
      },
      "2026-04-05": {
        "rain": 20.1,
        "tmean": 20.0
      },
      "2026-04-06": {
        "rain": 16.2,
        "tmean": 19.7
      },
      "2026-04-07": {
        "rain": 30.3,
        "tmean": 19.5
      },
      "2026-04-08": {
        "rain": 2.2,
        "tmean": 19.6
      },
      "2026-04-09": {
        "rain": 17.8,
        "tmean": 19.3
      },
      "2026-04-10": {
        "rain": 20.7,
        "tmean": 19.5
      },
      "2026-04-11": {
        "rain": 3.6,
        "tmean": 20.2
      },
      "2026-04-12": {
        "rain": 1.8,
        "tmean": 20.7
      },
      "2026-04-13": {
        "rain": 2.0,
        "tmean": 20.4
      },
      "2026-04-14": {
        "rain": 24.8,
        "tmean": 20.0
      },
      "2026-04-15": {
        "rain": 11.0,
        "tmean": 19.8
      },
      "2026-04-16": {
        "rain": 23.1,
        "tmean": 20.3
      },
      "2026-04-17": {
        "rain": 19.5,
        "tmean": 19.8
      },
      "2026-04-18": {
        "rain": 13.1,
        "tmean": 20.2
      },
      "2026-04-19": {
        "rain": 28.6,
        "tmean": 20.1
      },
      "2026-04-20": {
        "rain": 14.5,
        "tmean": 19.8
      },
      "2026-04-21": {
        "rain": 3.0,
        "tmean": 20.9
      },
      "2026-04-22": {
        "rain": 3.7,
        "tmean": 20.6
      },
      "2026-04-23": {
        "rain": 2.1,
        "tmean": 20.8
      },
      "2026-04-24": {
        "rain": 2.5,
        "tmean": 20.7
      },
      "2026-04-25": {
        "rain": 11.8,
        "tmean": 20.7
      },
      "2026-04-26": {
        "rain": 4.1,
        "tmean": 20.9
      },
      "2026-04-27": {
        "rain": 2.0,
        "tmean": 20.9
      },
      "2026-04-28": {
        "rain": 1.2,
        "tmean": 20.5
      },
      "2026-04-29": {
        "rain": 5.8,
        "tmean": 20.6
      },
      "2026-04-30": {
        "rain": 0.6,
        "tmean": 20.9
      },
      "2026-05-01": {
        "rain": 12.8,
        "tmean": 20.3
      },
      "2026-05-02": {
        "rain": 20.7,
        "tmean": 19.9
      },
      "2026-05-03": {
        "rain": 14.4,
        "tmean": 19.9
      },
      "2026-05-04": {
        "rain": 15.1,
        "tmean": 19.9
      },
      "2026-05-05": {
        "rain": 9.8,
        "tmean": 20.4
      },
      "2026-05-06": {
        "rain": 10.4,
        "tmean": 20.8
      },
      "2026-05-07": {
        "rain": 29.0,
        "tmean": 20.4
      },
      "2026-05-08": {
        "rain": 5.2,
        "tmean": 20.1
      },
      "2026-05-09": {
        "rain": 3.1,
        "tmean": 21.2
      },
      "2026-05-10": {
        "rain": 10.1,
        "tmean": 20.3
      },
      "2026-05-11": {
        "rain": 6.1,
        "tmean": 20.9
      },
      "2026-05-12": {
        "rain": 4.7,
        "tmean": 20.8
      },
      "2026-05-13": {
        "rain": 13.0,
        "tmean": 20.4
      },
      "2026-05-14": {
        "rain": 2.5,
        "tmean": 20.0
      },
      "2026-05-15": {
        "rain": 0.7,
        "tmean": 20.3
      },
      "2026-05-16": {
        "rain": 0.4,
        "tmean": 20.3
      },
      "2026-05-17": {
        "rain": 0.0,
        "tmean": 21.2
      },
      "2026-05-18": {
        "rain": 9.9,
        "tmean": 20.3
      },
      "2026-05-19": {
        "rain": 4.1,
        "tmean": 20.3
      },
      "2026-05-20": {
        "rain": 5.7,
        "tmean": 20.2
      },
      "2026-05-21": {
        "rain": 1.5,
        "tmean": 20.6
      },
      "2026-05-22": {
        "rain": 0.8,
        "tmean": 20.3
      },
      "2026-05-23": {
        "rain": 12.4,
        "tmean": 19.6
      },
      "2026-05-24": {
        "rain": 2.3,
        "tmean": 19.3
      }
    },
    "Java": {
      "2026-02-20": {
        "rain": 0.0,
        "tmean": null
      },
      "2026-02-21": {
        "rain": 0.0,
        "tmean": null
      },
      "2026-02-22": {
        "rain": 0.0,
        "tmean": null
      },
      "2026-02-23": {
        "rain": 0.0,
        "tmean": null
      },
      "2026-02-24": {
        "rain": 0.0,
        "tmean": null
      },
      "2026-02-25": {
        "rain": 0.0,
        "tmean": null
      },
      "2026-02-26": {
        "rain": 0.0,
        "tmean": null
      },
      "2026-02-27": {
        "rain": 0.0,
        "tmean": null
      },
      "2026-02-28": {
        "rain": 0.0,
        "tmean": null
      },
      "2026-03-01": {
        "rain": 0.0,
        "tmean": null
      },
      "2026-03-02": {
        "rain": 0.0,
        "tmean": null
      },
      "2026-03-03": {
        "rain": 0.0,
        "tmean": null
      },
      "2026-03-04": {
        "rain": 0.0,
        "tmean": null
      },
      "2026-03-05": {
        "rain": 0.0,
        "tmean": null
      },
      "2026-03-06": {
        "rain": 0.0,
        "tmean": null
      },
      "2026-03-07": {
        "rain": 0.0,
        "tmean": null
      },
      "2026-03-08": {
        "rain": 0.0,
        "tmean": null
      },
      "2026-03-09": {
        "rain": 0.0,
        "tmean": null
      },
      "2026-03-10": {
        "rain": 0.0,
        "tmean": null
      },
      "2026-03-11": {
        "rain": 4.1,
        "tmean": 25.4
      },
      "2026-03-12": {
        "rain": 3.4,
        "tmean": 25.4
      },
      "2026-03-13": {
        "rain": 16.3,
        "tmean": 24.9
      },
      "2026-03-14": {
        "rain": 58.7,
        "tmean": 24.8
      },
      "2026-03-15": {
        "rain": 26.4,
        "tmean": 24.8
      },
      "2026-03-16": {
        "rain": 15.1,
        "tmean": 24.7
      },
      "2026-03-17": {
        "rain": 13.6,
        "tmean": 24.9
      },
      "2026-03-18": {
        "rain": 10.3,
        "tmean": 25.2
      },
      "2026-03-19": {
        "rain": 9.3,
        "tmean": 25.1
      },
      "2026-03-20": {
        "rain": 13.6,
        "tmean": 24.9
      },
      "2026-03-21": {
        "rain": 48.5,
        "tmean": 24.6
      },
      "2026-03-22": {
        "rain": 14.0,
        "tmean": 24.4
      },
      "2026-03-23": {
        "rain": 16.0,
        "tmean": 22.3
      },
      "2026-03-24": {
        "rain": 14.5,
        "tmean": 20.7
      },
      "2026-03-25": {
        "rain": 19.3,
        "tmean": 20.9
      },
      "2026-03-26": {
        "rain": 0.5,
        "tmean": 24.4
      },
      "2026-03-27": {
        "rain": 3.2,
        "tmean": 25.6
      },
      "2026-03-28": {
        "rain": 16.3,
        "tmean": 25.4
      },
      "2026-03-29": {
        "rain": 0.7,
        "tmean": 24.9
      },
      "2026-03-30": {
        "rain": 8.0,
        "tmean": 24.5
      },
      "2026-03-31": {
        "rain": 0.5,
        "tmean": 25.4
      },
      "2026-04-01": {
        "rain": 0.0,
        "tmean": 26.0
      },
      "2026-04-02": {
        "rain": 6.7,
        "tmean": 25.6
      },
      "2026-04-03": {
        "rain": 2.5,
        "tmean": 24.7
      },
      "2026-04-04": {
        "rain": 0.7,
        "tmean": 25.5
      },
      "2026-04-05": {
        "rain": 2.1,
        "tmean": 25.2
      },
      "2026-04-06": {
        "rain": 0.4,
        "tmean": 25.2
      },
      "2026-04-07": {
        "rain": 3.6,
        "tmean": 25.4
      },
      "2026-04-08": {
        "rain": 1.4,
        "tmean": 25.5
      },
      "2026-04-09": {
        "rain": 0.8,
        "tmean": 25.0
      },
      "2026-04-10": {
        "rain": 2.9,
        "tmean": 25.3
      },
      "2026-04-11": {
        "rain": 5.5,
        "tmean": 25.0
      },
      "2026-04-12": {
        "rain": 0.6,
        "tmean": 25.1
      },
      "2026-04-13": {
        "rain": 0.1,
        "tmean": 25.7
      },
      "2026-04-14": {
        "rain": 0.3,
        "tmean": 26.2
      },
      "2026-04-15": {
        "rain": 0.1,
        "tmean": 26.3
      },
      "2026-04-16": {
        "rain": 0.0,
        "tmean": 26.1
      },
      "2026-04-17": {
        "rain": 0.0,
        "tmean": 26.0
      },
      "2026-04-18": {
        "rain": 0.0,
        "tmean": 25.9
      },
      "2026-04-19": {
        "rain": 0.0,
        "tmean": 25.7
      },
      "2026-04-20": {
        "rain": 0.2,
        "tmean": 25.8
      },
      "2026-04-21": {
        "rain": 32.7,
        "tmean": 24.7
      },
      "2026-04-22": {
        "rain": 0.6,
        "tmean": 25.9
      },
      "2026-04-23": {
        "rain": 5.3,
        "tmean": 25.5
      },
      "2026-04-24": {
        "rain": 0.0,
        "tmean": 26.4
      },
      "2026-04-25": {
        "rain": 0.0,
        "tmean": 26.8
      },
      "2026-04-26": {
        "rain": 3.1,
        "tmean": 26.2
      },
      "2026-04-27": {
        "rain": 11.0,
        "tmean": 24.7
      },
      "2026-04-28": {
        "rain": 8.6,
        "tmean": 25.3
      },
      "2026-04-29": {
        "rain": 12.6,
        "tmean": 25.0
      },
      "2026-04-30": {
        "rain": 0.4,
        "tmean": 24.9
      },
      "2026-05-01": {
        "rain": 22.0,
        "tmean": 24.1
      },
      "2026-05-02": {
        "rain": 1.1,
        "tmean": 25.2
      },
      "2026-05-03": {
        "rain": 0.0,
        "tmean": 26.0
      },
      "2026-05-04": {
        "rain": 0.0,
        "tmean": 25.9
      },
      "2026-05-05": {
        "rain": 0.0,
        "tmean": 26.1
      },
      "2026-05-06": {
        "rain": 0.0,
        "tmean": 26.1
      },
      "2026-05-07": {
        "rain": 0.0,
        "tmean": 25.9
      },
      "2026-05-08": {
        "rain": 0.0,
        "tmean": 26.4
      },
      "2026-05-09": {
        "rain": 0.3,
        "tmean": 26.7
      },
      "2026-05-10": {
        "rain": 0.6,
        "tmean": 26.5
      },
      "2026-05-11": {
        "rain": 0.0,
        "tmean": 26.7
      },
      "2026-05-12": {
        "rain": 0.0,
        "tmean": 26.2
      },
      "2026-05-13": {
        "rain": 0.0,
        "tmean": 26.1
      },
      "2026-05-14": {
        "rain": 0.2,
        "tmean": 26.1
      },
      "2026-05-15": {
        "rain": 0.0,
        "tmean": 26.3
      },
      "2026-05-16": {
        "rain": 3.5,
        "tmean": 26.1
      },
      "2026-05-17": {
        "rain": 3.6,
        "tmean": 25.9
      },
      "2026-05-18": {
        "rain": 4.1,
        "tmean": 25.7
      },
      "2026-05-19": {
        "rain": 2.2,
        "tmean": 26.1
      },
      "2026-05-20": {
        "rain": 1.0,
        "tmean": 26.3
      },
      "2026-05-21": {
        "rain": 1.4,
        "tmean": 26.5
      },
      "2026-05-22": {
        "rain": 1.0,
        "tmean": 26.1
      },
      "2026-05-23": {
        "rain": 0.6,
        "tmean": 26.2
      }
    },
    "Toraja": {
      "2026-02-20": {
        "rain": 0.0,
        "tmean": null
      },
      "2026-02-21": {
        "rain": 0.0,
        "tmean": null
      },
      "2026-02-22": {
        "rain": 0.0,
        "tmean": null
      },
      "2026-02-23": {
        "rain": 0.0,
        "tmean": null
      },
      "2026-02-24": {
        "rain": 0.0,
        "tmean": null
      },
      "2026-02-25": {
        "rain": 0.0,
        "tmean": null
      },
      "2026-02-26": {
        "rain": 0.0,
        "tmean": null
      },
      "2026-02-27": {
        "rain": 0.0,
        "tmean": null
      },
      "2026-02-28": {
        "rain": 0.0,
        "tmean": null
      },
      "2026-03-01": {
        "rain": 0.0,
        "tmean": null
      },
      "2026-03-02": {
        "rain": 0.0,
        "tmean": null
      },
      "2026-03-03": {
        "rain": 0.0,
        "tmean": null
      },
      "2026-03-04": {
        "rain": 0.0,
        "tmean": null
      },
      "2026-03-05": {
        "rain": 0.0,
        "tmean": null
      },
      "2026-03-06": {
        "rain": 0.0,
        "tmean": null
      },
      "2026-03-07": {
        "rain": 0.0,
        "tmean": null
      },
      "2026-03-08": {
        "rain": 0.0,
        "tmean": null
      },
      "2026-03-09": {
        "rain": 0.0,
        "tmean": null
      },
      "2026-03-10": {
        "rain": 0.0,
        "tmean": null
      },
      "2026-03-11": {
        "rain": 4.8,
        "tmean": 21.8
      },
      "2026-03-12": {
        "rain": 2.3,
        "tmean": 21.5
      },
      "2026-03-13": {
        "rain": 4.8,
        "tmean": 22.1
      },
      "2026-03-14": {
        "rain": 6.0,
        "tmean": 22.1
      },
      "2026-03-15": {
        "rain": 26.8,
        "tmean": 22.2
      },
      "2026-03-16": {
        "rain": 33.1,
        "tmean": 22.0
      },
      "2026-03-17": {
        "rain": 3.4,
        "tmean": 22.4
      },
      "2026-03-18": {
        "rain": 20.8,
        "tmean": 22.3
      },
      "2026-03-19": {
        "rain": 17.3,
        "tmean": 22.6
      },
      "2026-03-20": {
        "rain": 60.8,
        "tmean": 21.1
      },
      "2026-03-21": {
        "rain": 18.7,
        "tmean": 21.7
      },
      "2026-03-22": {
        "rain": 19.5,
        "tmean": 21.3
      },
      "2026-03-23": {
        "rain": 7.1,
        "tmean": 23.2
      },
      "2026-03-24": {
        "rain": 11.3,
        "tmean": 25.0
      },
      "2026-03-25": {
        "rain": 6.3,
        "tmean": 24.9
      },
      "2026-03-26": {
        "rain": 5.6,
        "tmean": 23.2
      },
      "2026-03-27": {
        "rain": 4.2,
        "tmean": 21.9
      },
      "2026-03-28": {
        "rain": 1.4,
        "tmean": 21.7
      },
      "2026-03-29": {
        "rain": 5.8,
        "tmean": 21.4
      },
      "2026-03-30": {
        "rain": 5.2,
        "tmean": 21.1
      },
      "2026-03-31": {
        "rain": 11.6,
        "tmean": 21.4
      },
      "2026-04-01": {
        "rain": 6.9,
        "tmean": 21.5
      },
      "2026-04-02": {
        "rain": 3.8,
        "tmean": 21.9
      },
      "2026-04-03": {
        "rain": 31.4,
        "tmean": 21.3
      },
      "2026-04-04": {
        "rain": 1.5,
        "tmean": 22.1
      },
      "2026-04-05": {
        "rain": 18.5,
        "tmean": 21.4
      },
      "2026-04-06": {
        "rain": 2.5,
        "tmean": 21.8
      },
      "2026-04-07": {
        "rain": 12.4,
        "tmean": 21.9
      },
      "2026-04-08": {
        "rain": 5.8,
        "tmean": 21.9
      },
      "2026-04-09": {
        "rain": 7.0,
        "tmean": 21.6
      },
      "2026-04-10": {
        "rain": 2.2,
        "tmean": 21.7
      },
      "2026-04-11": {
        "rain": 10.3,
        "tmean": 21.3
      },
      "2026-04-12": {
        "rain": 6.4,
        "tmean": 21.5
      },
      "2026-04-13": {
        "rain": 2.7,
        "tmean": 20.9
      },
      "2026-04-14": {
        "rain": 0.8,
        "tmean": 21.5
      },
      "2026-04-15": {
        "rain": 3.6,
        "tmean": 21.2
      },
      "2026-04-16": {
        "rain": 4.5,
        "tmean": 21.2
      },
      "2026-04-17": {
        "rain": 7.4,
        "tmean": 21.5
      },
      "2026-04-18": {
        "rain": 2.5,
        "tmean": 21.5
      },
      "2026-04-19": {
        "rain": 7.7,
        "tmean": 21.7
      },
      "2026-04-20": {
        "rain": 3.0,
        "tmean": 21.7
      },
      "2026-04-21": {
        "rain": 2.2,
        "tmean": 22.3
      },
      "2026-04-22": {
        "rain": 2.4,
        "tmean": 22.4
      },
      "2026-04-23": {
        "rain": 1.9,
        "tmean": 22.2
      },
      "2026-04-24": {
        "rain": 0.1,
        "tmean": 22.8
      },
      "2026-04-25": {
        "rain": 6.5,
        "tmean": 23.0
      },
      "2026-04-26": {
        "rain": 3.0,
        "tmean": 22.5
      },
      "2026-04-27": {
        "rain": 16.4,
        "tmean": 21.8
      },
      "2026-04-28": {
        "rain": 12.6,
        "tmean": 21.7
      },
      "2026-04-29": {
        "rain": 5.1,
        "tmean": 21.8
      },
      "2026-04-30": {
        "rain": 3.2,
        "tmean": 22.1
      },
      "2026-05-01": {
        "rain": 21.7,
        "tmean": 21.4
      },
      "2026-05-02": {
        "rain": 17.2,
        "tmean": 21.6
      },
      "2026-05-03": {
        "rain": 5.4,
        "tmean": 21.2
      },
      "2026-05-04": {
        "rain": 7.9,
        "tmean": 21.4
      },
      "2026-05-05": {
        "rain": 9.4,
        "tmean": 21.0
      },
      "2026-05-06": {
        "rain": 2.9,
        "tmean": 21.0
      },
      "2026-05-07": {
        "rain": 7.5,
        "tmean": 22.0
      },
      "2026-05-08": {
        "rain": 6.7,
        "tmean": 21.4
      },
      "2026-05-09": {
        "rain": 5.9,
        "tmean": 21.5
      },
      "2026-05-10": {
        "rain": 12.6,
        "tmean": 21.5
      },
      "2026-05-11": {
        "rain": 3.3,
        "tmean": 22.6
      },
      "2026-05-12": {
        "rain": 8.2,
        "tmean": 22.8
      },
      "2026-05-13": {
        "rain": 3.1,
        "tmean": 23.0
      },
      "2026-05-14": {
        "rain": 7.8,
        "tmean": 22.9
      },
      "2026-05-15": {
        "rain": 21.5,
        "tmean": 22.6
      },
      "2026-05-16": {
        "rain": 10.0,
        "tmean": 22.8
      },
      "2026-05-17": {
        "rain": 12.1,
        "tmean": 21.7
      },
      "2026-05-18": {
        "rain": 6.2,
        "tmean": 21.6
      },
      "2026-05-19": {
        "rain": 11.4,
        "tmean": 21.7
      },
      "2026-05-20": {
        "rain": 5.9,
        "tmean": 21.5
      },
      "2026-05-21": {
        "rain": 3.8,
        "tmean": 22.4
      },
      "2026-05-22": {
        "rain": 7.7,
        "tmean": 22.0
      },
      "2026-05-23": {
        "rain": 15.5,
        "tmean": 22.3
      },
      "2026-05-24": {
        "rain": 20.7,
        "tmean": 21.7
      }
    },
    "Flores": {
      "2026-02-21": {
        "rain": 0.0,
        "tmean": null
      },
      "2026-02-22": {
        "rain": 0.0,
        "tmean": null
      },
      "2026-02-23": {
        "rain": 0.0,
        "tmean": null
      },
      "2026-02-24": {
        "rain": 0.0,
        "tmean": null
      },
      "2026-02-25": {
        "rain": 0.0,
        "tmean": null
      },
      "2026-02-26": {
        "rain": 0.0,
        "tmean": null
      },
      "2026-02-27": {
        "rain": 0.0,
        "tmean": null
      },
      "2026-02-28": {
        "rain": 0.0,
        "tmean": null
      },
      "2026-03-01": {
        "rain": 0.0,
        "tmean": null
      },
      "2026-03-02": {
        "rain": 0.0,
        "tmean": null
      },
      "2026-03-03": {
        "rain": 0.0,
        "tmean": null
      },
      "2026-03-04": {
        "rain": 0.0,
        "tmean": null
      },
      "2026-03-05": {
        "rain": 0.0,
        "tmean": null
      },
      "2026-03-06": {
        "rain": 0.0,
        "tmean": null
      },
      "2026-03-07": {
        "rain": 0.0,
        "tmean": null
      },
      "2026-03-08": {
        "rain": 0.0,
        "tmean": null
      },
      "2026-03-09": {
        "rain": 0.0,
        "tmean": null
      },
      "2026-03-10": {
        "rain": 0.0,
        "tmean": null
      },
      "2026-03-11": {
        "rain": 4.5,
        "tmean": 18.3
      },
      "2026-03-12": {
        "rain": 2.1,
        "tmean": 18.5
      },
      "2026-03-13": {
        "rain": 6.0,
        "tmean": 18.7
      },
      "2026-03-14": {
        "rain": 8.6,
        "tmean": 18.6
      },
      "2026-03-15": {
        "rain": 11.5,
        "tmean": 18.8
      },
      "2026-03-16": {
        "rain": 1.2,
        "tmean": 19.0
      },
      "2026-03-17": {
        "rain": 0.0,
        "tmean": 19.0
      },
      "2026-03-18": {
        "rain": 3.3,
        "tmean": 19.5
      },
      "2026-03-19": {
        "rain": 4.5,
        "tmean": 19.1
      },
      "2026-03-20": {
        "rain": 1.3,
        "tmean": 17.6
      },
      "2026-03-21": {
        "rain": 0.7,
        "tmean": 19.0
      },
      "2026-03-22": {
        "rain": 2.0,
        "tmean": 19.1
      },
      "2026-03-23": {
        "rain": 1.9,
        "tmean": 19.9
      },
      "2026-03-24": {
        "rain": 5.1,
        "tmean": 20.5
      },
      "2026-03-25": {
        "rain": 6.9,
        "tmean": 20.6
      },
      "2026-03-26": {
        "rain": 4.5,
        "tmean": 19.7
      },
      "2026-03-27": {
        "rain": 1.8,
        "tmean": 19.4
      },
      "2026-03-28": {
        "rain": 2.0,
        "tmean": 19.2
      },
      "2026-03-29": {
        "rain": 2.2,
        "tmean": 18.8
      },
      "2026-03-30": {
        "rain": 3.0,
        "tmean": 18.6
      },
      "2026-03-31": {
        "rain": 27.2,
        "tmean": 18.3
      },
      "2026-04-01": {
        "rain": 2.2,
        "tmean": 18.6
      },
      "2026-04-02": {
        "rain": 3.8,
        "tmean": 18.8
      },
      "2026-04-03": {
        "rain": 1.3,
        "tmean": 18.9
      },
      "2026-04-04": {
        "rain": 1.8,
        "tmean": 19.1
      },
      "2026-04-05": {
        "rain": 2.0,
        "tmean": 19.2
      },
      "2026-04-06": {
        "rain": 2.0,
        "tmean": 19.1
      },
      "2026-04-07": {
        "rain": 15.0,
        "tmean": 19.0
      },
      "2026-04-08": {
        "rain": 3.1,
        "tmean": 19.1
      },
      "2026-04-09": {
        "rain": 4.9,
        "tmean": 18.9
      },
      "2026-04-10": {
        "rain": 2.4,
        "tmean": 18.8
      },
      "2026-04-11": {
        "rain": 7.1,
        "tmean": 18.7
      },
      "2026-04-12": {
        "rain": 0.9,
        "tmean": 18.8
      },
      "2026-04-13": {
        "rain": 0.0,
        "tmean": 18.5
      },
      "2026-04-14": {
        "rain": 1.8,
        "tmean": 18.5
      },
      "2026-04-15": {
        "rain": 2.1,
        "tmean": 17.7
      },
      "2026-04-16": {
        "rain": 1.0,
        "tmean": 17.9
      },
      "2026-04-17": {
        "rain": 0.0,
        "tmean": 17.9
      },
      "2026-04-18": {
        "rain": 1.3,
        "tmean": 18.1
      },
      "2026-04-19": {
        "rain": 14.3,
        "tmean": 18.5
      },
      "2026-04-20": {
        "rain": 27.3,
        "tmean": 18.7
      },
      "2026-04-21": {
        "rain": 1.7,
        "tmean": 19.4
      },
      "2026-04-22": {
        "rain": 0.0,
        "tmean": 19.8
      },
      "2026-04-23": {
        "rain": 4.2,
        "tmean": 19.3
      },
      "2026-04-24": {
        "rain": 1.7,
        "tmean": 20.1
      },
      "2026-04-25": {
        "rain": 2.6,
        "tmean": 19.2
      },
      "2026-04-26": {
        "rain": 19.2,
        "tmean": 19.0
      },
      "2026-04-27": {
        "rain": 13.6,
        "tmean": 19.1
      },
      "2026-04-28": {
        "rain": 3.6,
        "tmean": 18.8
      },
      "2026-04-29": {
        "rain": 5.9,
        "tmean": 19.0
      },
      "2026-04-30": {
        "rain": 9.0,
        "tmean": 18.9
      },
      "2026-05-01": {
        "rain": 4.0,
        "tmean": 18.5
      },
      "2026-05-02": {
        "rain": 0.0,
        "tmean": 18.4
      },
      "2026-05-03": {
        "rain": 1.6,
        "tmean": 18.3
      },
      "2026-05-04": {
        "rain": 1.6,
        "tmean": 18.4
      },
      "2026-05-05": {
        "rain": 0.7,
        "tmean": 18.9
      },
      "2026-05-06": {
        "rain": 2.6,
        "tmean": 18.7
      },
      "2026-05-07": {
        "rain": 0.6,
        "tmean": 18.8
      },
      "2026-05-08": {
        "rain": 3.8,
        "tmean": 18.2
      },
      "2026-05-09": {
        "rain": 4.1,
        "tmean": 17.9
      },
      "2026-05-10": {
        "rain": 2.0,
        "tmean": 18.4
      },
      "2026-05-11": {
        "rain": 1.7,
        "tmean": 19.1
      },
      "2026-05-12": {
        "rain": 3.0,
        "tmean": 19.7
      },
      "2026-05-13": {
        "rain": 6.6,
        "tmean": 19.8
      },
      "2026-05-14": {
        "rain": 4.1,
        "tmean": 19.9
      },
      "2026-05-15": {
        "rain": 13.8,
        "tmean": 19.4
      },
      "2026-05-16": {
        "rain": 8.0,
        "tmean": 19.4
      },
      "2026-05-17": {
        "rain": 15.2,
        "tmean": 19.2
      },
      "2026-05-18": {
        "rain": 28.9,
        "tmean": 18.4
      },
      "2026-05-19": {
        "rain": 5.8,
        "tmean": 19.0
      },
      "2026-05-20": {
        "rain": 5.6,
        "tmean": 18.6
      },
      "2026-05-21": {
        "rain": 0.1,
        "tmean": 19.5
      },
      "2026-05-22": {
        "rain": 7.1,
        "tmean": 19.0
      },
      "2026-05-23": {
        "rain": 3.5,
        "tmean": 18.7
      },
      "2026-05-24": {
        "rain": 0.2,
        "tmean": 18.8
      }
    }
  }
}
