{
  "currency_index": {
    "scraped_at": "2026-07-20T22:30:36.451425+00:00",
    "index_value": 108.577996,
    "daily_delta_i": 0.0,
    "daily_delta_pct": 0.0,
    "zscore": 1.868537,
    "zscore_mean": 104.810967,
    "zscore_std": 2.016031,
    "currencies": [
      {
        "ticker": "BRL=X",
        "name": "Brazilian Real",
        "type": "export",
        "weight": 0.513,
        "daily_chg": -0.0,
        "contribution": -0.0
      },
      {
        "ticker": "VND=X",
        "name": "Vietnamese Dong",
        "type": "export",
        "weight": 0.262,
        "daily_chg": -0.0,
        "contribution": -0.0
      },
      {
        "ticker": "COP=X",
        "name": "Colombian Peso",
        "type": "export",
        "weight": 0.128,
        "daily_chg": -0.0,
        "contribution": -0.0
      },
      {
        "ticker": "IDR=X",
        "name": "Indonesian Rupiah",
        "type": "export",
        "weight": 0.051,
        "daily_chg": -0.0,
        "contribution": -0.0
      },
      {
        "ticker": "PEN=X",
        "name": "Peruvian Sol",
        "type": "export",
        "weight": 0.047,
        "daily_chg": -0.0,
        "contribution": -0.0
      },
      {
        "ticker": "EURUSD=X",
        "name": "Euro",
        "type": "import",
        "weight": 0.673,
        "daily_chg": 0.0,
        "contribution": -0.0
      },
      {
        "ticker": "JPY=X",
        "name": "Japanese Yen",
        "type": "import",
        "weight": 0.095,
        "daily_chg": -0.0,
        "contribution": 0.0
      },
      {
        "ticker": "CHF=X",
        "name": "Swiss Franc",
        "type": "import",
        "weight": 0.052,
        "daily_chg": -0.0,
        "contribution": 0.0
      },
      {
        "ticker": "CNY=X",
        "name": "Chinese Yuan",
        "type": "import",
        "weight": 0.052,
        "daily_chg": -0.0,
        "contribution": 0.0
      },
      {
        "ticker": "CAD=X",
        "name": "Canadian Dollar",
        "type": "import",
        "weight": 0.046,
        "daily_chg": -0.0,
        "contribution": 0.0
      },
      {
        "ticker": "KRW=X",
        "name": "South Korean Won",
        "type": "import",
        "weight": 0.045,
        "daily_chg": -0.0,
        "contribution": 0.0
      },
      {
        "ticker": "GBP=X",
        "name": "British Pound",
        "type": "import",
        "weight": 0.038,
        "daily_chg": -0.0,
        "contribution": 0.0
      }
    ],
    "history": [
      {
        "date": "2026-06-21",
        "value": 107.184533
      },
      {
        "date": "2026-06-22",
        "value": 107.467092
      },
      {
        "date": "2026-06-23",
        "value": 107.585698
      },
      {
        "date": "2026-06-24",
        "value": 107.610077
      },
      {
        "date": "2026-06-25",
        "value": 107.515525
      },
      {
        "date": "2026-06-26",
        "value": 107.550602
      },
      {
        "date": "2026-06-27",
        "value": 107.599122
      },
      {
        "date": "2026-06-28",
        "value": 107.648909
      },
      {
        "date": "2026-06-29",
        "value": 107.724611
      },
      {
        "date": "2026-06-30",
        "value": 107.488486
      },
      {
        "date": "2026-07-01",
        "value": 107.734702
      },
      {
        "date": "2026-07-02",
        "value": 107.445927
      },
      {
        "date": "2026-07-03",
        "value": 107.047429
      },
      {
        "date": "2026-07-04",
        "value": 107.613534
      },
      {
        "date": "2026-07-05",
        "value": 107.561189
      },
      {
        "date": "2026-07-06",
        "value": 107.729945
      },
      {
        "date": "2026-07-07",
        "value": 107.938593
      },
      {
        "date": "2026-07-08",
        "value": 107.822141
      },
      {
        "date": "2026-07-09",
        "value": 107.790681
      },
      {
        "date": "2026-07-10",
        "value": 107.99435
      },
      {
        "date": "2026-07-11",
        "value": 108.808146
      },
      {
        "date": "2026-07-12",
        "value": 108.726677
      },
      {
        "date": "2026-07-13",
        "value": 108.940582
      },
      {
        "date": "2026-07-14",
        "value": 108.596574
      },
      {
        "date": "2026-07-15",
        "value": 108.762907
      },
      {
        "date": "2026-07-16",
        "value": 108.616136
      },
      {
        "date": "2026-07-17",
        "value": 108.625896
      },
      {
        "date": "2026-07-18",
        "value": 108.48325
      },
      {
        "date": "2026-07-19",
        "value": 108.577996
      },
      {
        "date": "2026-07-20",
        "value": 108.577996
      }
    ]
  },
  "scraped_at": "2026-07-20T22:31:12.705111Z",
  "sentiment": {
    "available": true,
    "scraped_at": "2026-07-20T22:31:11.287614Z",
    "overall_sentiment": "Neutral",
    "overall_confidence": 91.1,
    "net_index": -5.4,
    "bull_count": 6,
    "bear_count": 8,
    "neutral_count": 9,
    "total": 23,
    "items": [
      {
        "headline": "Café fecha em alta nas bolsas com mercado ainda sustentado por atraso da safra brasileira",
        "source": "Notícias Agrícolas",
        "sentiment": "Bullish",
        "confidence": 90.0,
        "tags": [
          "cafe",
          "noticias_agricolas"
        ]
      },
      {
        "headline": "Rejoice! Pope Leo Loves Drinking Coffee (And He Likes It Strong)",
        "source": "Sprudge",
        "sentiment": "Neutral",
        "confidence": 95.0,
        "tags": [
          "sprudge"
        ]
      },
      {
        "headline": "Colheita de café supera metade do previsto na área de atuação da Expocacer",
        "source": "Notícias Agrícolas",
        "sentiment": "Bearish",
        "confidence": 65.0,
        "tags": [
          "cafe",
          "noticias_agricolas"
        ]
      },
      {
        "headline": "Café amplia ganhos em Nova York com atraso da colheita no Brasil; robusta opera perto da estabilidade",
        "source": "Notícias Agrícolas",
        "sentiment": "Bullish",
        "confidence": 90.0,
        "tags": [
          "cafe",
          "noticias_agricolas"
        ]
      },
      {
        "headline": "Build-Outs Of Coffee: Blue Sparrow Coffee In Denver, CO",
        "source": "Sprudge",
        "sentiment": "Neutral",
        "confidence": 95.0,
        "tags": [
          "sprudge"
        ]
      },
      {
        "headline": "Café abre a semana com leves oscilações nas bolsas e mercado segue atento ao ritmo da colheita no Brasil",
        "source": "Notícias Agrícolas",
        "sentiment": "Neutral",
        "confidence": 85.0,
        "tags": [
          "cafe",
          "noticias_agricolas"
        ]
      },
      {
        "headline": "Café encerra semana em alta com atraso da colheita no Brasil sustentando as cotações",
        "source": "Notícias Agrícolas",
        "sentiment": "Bullish",
        "confidence": 90.0,
        "tags": [
          "cafe",
          "noticias_agricolas"
        ]
      },
      {
        "headline": "Colheita de café do Brasil atinge 64% do total, mas segue atrasada, diz Safras & Mercado",
        "source": "Notícias Agrícolas",
        "sentiment": "Bullish",
        "confidence": 85.0,
        "tags": [
          "cafe",
          "noticias_agricolas"
        ]
      },
      {
        "headline": "Café abre sem direção única nas bolsas após forte volatilidade; mercado acompanha cenário comercial e oferta global",
        "source": "Notícias Agrícolas",
        "sentiment": "Neutral",
        "confidence": 85.0,
        "tags": [
          "cafe",
          "noticias_agricolas"
        ]
      },
      {
        "headline": "CNC representa o cooperativismo cafeeiro no 17º Workshop do Produtor Rural promovido pelo Sicoob",
        "source": "Notícias Agrícolas",
        "sentiment": "Neutral",
        "confidence": 95.0,
        "tags": [
          "cafe",
          "noticias_agricolas"
        ]
      },
      {
        "headline": "Some Green Coffee Importers Are Now Issuing Tariff Refunds",
        "source": "Sprudge",
        "sentiment": "Bearish",
        "confidence": 75.0,
        "tags": [
          "sprudge"
        ]
      },
      {
        "headline": "Café despenca nas bolsas e encerra sessão com perdas superiores a 4% em Nova York diante do avanço da colheita no Brasil",
        "source": "Notícias Agrícolas",
        "sentiment": "Bearish",
        "confidence": 90.0,
        "tags": [
          "cafe",
          "noticias_agricolas"
        ]
      },
      {
        "headline": "Entidades celebram isenção de todos os cafés do Brasil do tarifaço de 25% dos EUA",
        "source": "Notícias Agrícolas",
        "sentiment": "Bearish",
        "confidence": 85.0,
        "tags": [
          "cafe",
          "noticias_agricolas"
        ]
      },
      {
        "headline": "BSCA celebra isenção dos cafés do Brasil do tarifaço de 25% dos EUA",
        "source": "Notícias Agrícolas",
        "sentiment": "Bearish",
        "confidence": 85.0,
        "tags": [
          "cafe",
          "noticias_agricolas"
        ]
      },
      {
        "headline": "Café amplia perdas nas bolsas com pressão técnica e cautela sobre a safra brasileira",
        "source": "Notícias Agrícolas",
        "sentiment": "Bearish",
        "confidence": 70.0,
        "tags": [
          "cafe",
          "noticias_agricolas"
        ]
      },
      {
        "headline": "Build-Outs Of Coffee: The Wild Fox In San Francisco, CA",
        "source": "Sprudge",
        "sentiment": "Neutral",
        "confidence": 95.0,
        "tags": [
          "sprudge"
        ]
      },
      {
        "headline": "Preços do café no Vietnã sobem em mercado com baixa atividade",
        "source": "Notícias Agrícolas",
        "sentiment": "Bullish",
        "confidence": 70.0,
        "tags": [
          "cafe",
          "noticias_agricolas"
        ]
      },
      {
        "headline": "Café solúvel do Brasil passa a ficar isento de tarifas dos EUA e garante exportações",
        "source": "Notícias Agrícolas",
        "sentiment": "Bearish",
        "confidence": 85.0,
        "tags": [
          "cafe",
          "noticias_agricolas"
        ]
      },
      {
        "headline": "Café abre em queda nas bolsas, mas mercado segue sustentado por oferta restrita e ritmo lento da safra brasileira",
        "source": "Notícias Agrícolas",
        "sentiment": "Bullish",
        "confidence": 75.0,
        "tags": [
          "cafe",
          "noticias_agricolas"
        ]
      },
      {
        "headline": "Exportação de café do Brasil pode saltar em 26/27, mas há desafios na qualidade, diz Cecafé",
        "source": "Notícias Agrícolas",
        "sentiment": "Bearish",
        "confidence": 70.0,
        "tags": [
          "cafe",
          "noticias_agricolas"
        ]
      },
      {
        "headline": "Build-Outs Of Coffee: Nandan Coffee In Bangalore, India",
        "source": "Sprudge",
        "sentiment": "Neutral",
        "confidence": 95.0,
        "tags": [
          "sprudge"
        ]
      },
      {
        "headline": "America’s Next Hotbed For Coffee Production Is… Florida?",
        "source": "Sprudge",
        "sentiment": "Neutral",
        "confidence": 80.0,
        "tags": [
          "sprudge"
        ]
      },
      {
        "headline": "In Washington, D.C., Coffee Meets Fine Dining At Jônt",
        "source": "Sprudge",
        "sentiment": "Neutral",
        "confidence": 95.0,
        "tags": [
          "sprudge"
        ]
      }
    ]
  },
  "robusta_factors": {
    "available": false,
    "reason": "robusta crashed: 'CotWeekly' object has no attribute 'mm_long'"
  },
  "sentiment_calibration": {
    "available": false,
    "warmup": true,
    "reason": "accumulating — 1/8 paired days",
    "n": 1,
    "min_sample": 8,
    "horizon_days": 5
  },
  "open_direction": {
    "available": true,
    "as_of": "2026-07-20",
    "for_session": "2026-07-21",
    "scraped_at": "2026-07-21T06:08:53.831176Z",
    "direction": "Abstain",
    "base_margin": -0.141154606590719,
    "final_margin": -0.10753425388813195,
    "base_prob": 0.4647698245999405,
    "final_prob": 0.47314231253953926,
    "prob_up": 0.47314231253953926,
    "prob_down": 0.5268576874604607,
    "regime": {
      "ny_shock": false,
      "vol_regime": "high",
      "vol_percentile": 0.87,
      "harvest_weight": 0.2,
      "harvest_active": false,
      "brent_overnight_pct": null,
      "oil_shock": false
    },
    "expected_gap_pct": -0.034,
    "expected_gap_usd_mt": -1.3,
    "features": [
      {
        "var_name": "days_since_roll",
        "label": "Roll-Cycle Position",
        "raw_value": 33.0,
        "raw_fmt": "day 33",
        "z": 1.18,
        "usd_per_ton": null,
        "phi": 0.19670223284763055,
        "detail": {
          "text": "day 33 of the bi-monthly front-contract cycle — gaps historically tilt down mid-cycle (~day 10), up late-cycle"
        }
      },
      {
        "var_name": "kc_after_rc_diff",
        "label": "NY after RC-Close Move",
        "raw_value": -0.0015432098765432167,
        "raw_fmt": "-0.15%",
        "z": -0.39,
        "usd_per_ton": -6.0,
        "phi": -0.16308188014504352,
        "detail": {
          "text": "KC at RC close (17:30 London) 324.00¢/lb → KC close (18:30) 323.50¢/lb = -11.0 $/t on arabica; -0.15% mapped on robusta ≈ -6.0 $/t"
        }
      }
    ],
    "target": {
      "kind": "overnight_gap",
      "definition": "RC first-bar open ÷ prior 17:30-London close − 1; roll days excluded",
      "abstain_band": 0.1
    },
    "model": {
      "kind": "logistic_regression_l2",
      "active_features": [
        "kc_after_rc_diff",
        "days_since_roll"
      ],
      "n_features": 2,
      "n_train": 1162,
      "test_accuracy": 0.5747252747252747,
      "baseline_accuracy": 0.5351648351648352,
      "edge": 0.03956043956043953,
      "acted_accuracy": 0.6388059701492538,
      "acted_n": 335,
      "abstain_rate": 0.6318681318681318,
      "eval_method": "walk_forward",
      "n_test": 910,
      "mag_mae_pct": 0.30269555226243555,
      "mag_baseline_mae_pct": 0.3101684840872212,
      "mag_skill": 0.02409313714376038,
      "cci_available": false,
      "intraday_source": "barchart_15min",
      "roll_days_excluded": 88
    },
    "track": {
      "live_graded": 6,
      "live_hit_rate": 0.8333,
      "rolling_hit_rate": 0.8333,
      "rolling_n": 6,
      "cold_streak": false
    }
  }
}