{
  "currency_index": {
    "scraped_at": "2026-07-14T22:30:44.361112+00:00",
    "index_value": 109.010698,
    "daily_delta_i": -0.003159,
    "daily_delta_pct": -0.315777,
    "zscore": 2.018763,
    "zscore_mean": 105.098509,
    "zscore_std": 1.937914,
    "currencies": [
      {
        "ticker": "BRL=X",
        "name": "Brazilian Real",
        "type": "export",
        "weight": 0.513,
        "daily_chg": -0.697984,
        "contribution": -0.003581
      },
      {
        "ticker": "VND=X",
        "name": "Vietnamese Dong",
        "type": "export",
        "weight": 0.262,
        "daily_chg": 0.059065,
        "contribution": 0.000155
      },
      {
        "ticker": "COP=X",
        "name": "Colombian Peso",
        "type": "export",
        "weight": 0.128,
        "daily_chg": 0.273804,
        "contribution": 0.00035
      },
      {
        "ticker": "IDR=X",
        "name": "Indonesian Rupiah",
        "type": "export",
        "weight": 0.051,
        "daily_chg": 0.168816,
        "contribution": 8.6e-05
      },
      {
        "ticker": "PEN=X",
        "name": "Peruvian Sol",
        "type": "export",
        "weight": 0.047,
        "daily_chg": -0.524073,
        "contribution": -0.000246
      },
      {
        "ticker": "EURUSD=X",
        "name": "Euro",
        "type": "import",
        "weight": 0.673,
        "daily_chg": -0.036904,
        "contribution": 0.000248
      },
      {
        "ticker": "JPY=X",
        "name": "Japanese Yen",
        "type": "import",
        "weight": 0.095,
        "daily_chg": -0.145079,
        "contribution": 0.000138
      },
      {
        "ticker": "CHF=X",
        "name": "Swiss Franc",
        "type": "import",
        "weight": 0.052,
        "daily_chg": -0.439753,
        "contribution": 0.000229
      },
      {
        "ticker": "CNY=X",
        "name": "Chinese Yuan",
        "type": "import",
        "weight": 0.052,
        "daily_chg": 0.009075,
        "contribution": -5e-06
      },
      {
        "ticker": "CAD=X",
        "name": "Canadian Dollar",
        "type": "import",
        "weight": 0.046,
        "daily_chg": 0.233916,
        "contribution": -0.000108
      },
      {
        "ticker": "KRW=X",
        "name": "South Korean Won",
        "type": "import",
        "weight": 0.045,
        "daily_chg": 1.063581,
        "contribution": -0.000479
      },
      {
        "ticker": "GBP=X",
        "name": "British Pound",
        "type": "import",
        "weight": 0.038,
        "daily_chg": -0.142004,
        "contribution": 5.4e-05
      }
    ],
    "history": [
      {
        "date": "2026-06-15",
        "value": 107.280873
      },
      {
        "date": "2026-06-16",
        "value": 107.489334
      },
      {
        "date": "2026-06-17",
        "value": 107.086673
      },
      {
        "date": "2026-06-18",
        "value": 107.441715
      },
      {
        "date": "2026-06-19",
        "value": 107.711377
      },
      {
        "date": "2026-06-20",
        "value": 107.674982
      },
      {
        "date": "2026-06-21",
        "value": 107.593272
      },
      {
        "date": "2026-06-22",
        "value": 107.87691
      },
      {
        "date": "2026-06-23",
        "value": 107.995968
      },
      {
        "date": "2026-06-24",
        "value": 108.02044
      },
      {
        "date": "2026-06-25",
        "value": 107.925527
      },
      {
        "date": "2026-06-26",
        "value": 107.960738
      },
      {
        "date": "2026-06-27",
        "value": 108.009443
      },
      {
        "date": "2026-06-28",
        "value": 108.05942
      },
      {
        "date": "2026-06-29",
        "value": 108.13541
      },
      {
        "date": "2026-06-30",
        "value": 107.898385
      },
      {
        "date": "2026-07-01",
        "value": 108.14554
      },
      {
        "date": "2026-07-02",
        "value": 107.855663
      },
      {
        "date": "2026-07-03",
        "value": 107.455646
      },
      {
        "date": "2026-07-04",
        "value": 108.02391
      },
      {
        "date": "2026-07-05",
        "value": 107.971365
      },
      {
        "date": "2026-07-06",
        "value": 108.140764
      },
      {
        "date": "2026-07-07",
        "value": 108.350208
      },
      {
        "date": "2026-07-08",
        "value": 108.233312
      },
      {
        "date": "2026-07-09",
        "value": 108.201733
      },
      {
        "date": "2026-07-10",
        "value": 108.406178
      },
      {
        "date": "2026-07-11",
        "value": 109.223077
      },
      {
        "date": "2026-07-12",
        "value": 109.141298
      },
      {
        "date": "2026-07-13",
        "value": 109.356019
      },
      {
        "date": "2026-07-14",
        "value": 109.010698
      }
    ]
  },
  "scraped_at": "2026-07-14T22:31:08.923937Z",
  "sentiment": {
    "available": true,
    "scraped_at": "2026-07-14T22:31:07.381396Z",
    "overall_sentiment": "Bullish",
    "overall_confidence": 67.0,
    "net_index": 25.0,
    "bull_count": 5,
    "bear_count": 2,
    "neutral_count": 1,
    "total": 8,
    "items": [
      {
        "headline": "In Washington, D.C., Coffee Meets Fine Dining At Jônt",
        "source": "Sprudge",
        "sentiment": "Bullish",
        "confidence": 50.0,
        "tags": [
          "sprudge"
        ]
      },
      {
        "headline": "Build-Outs Of Coffee: Coffee Equipment Pros In Spicewood, TX",
        "source": "Sprudge",
        "sentiment": "Bullish",
        "confidence": 65.0,
        "tags": [
          "sprudge"
        ]
      },
      {
        "headline": "The Dog Days Of Coffee Are Here",
        "source": "Sprudge",
        "sentiment": "Bearish",
        "confidence": 60.0,
        "tags": [
          "sprudge"
        ]
      },
      {
        "headline": "New Study Finds Drinking Coffee Protects Against Liver Disease, Cancer, And Death",
        "source": "Sprudge",
        "sentiment": "Bullish",
        "confidence": 85.0,
        "tags": [
          "sprudge"
        ]
      },
      {
        "headline": "The San Franciscan Roaster Company Enters New Chapter Under New Ownership And Leadership",
        "source": "Sprudge",
        "sentiment": "Neutral",
        "confidence": 95.0,
        "tags": [
          "sprudge"
        ]
      },
      {
        "headline": "The Afternoon Coffee Crash Is A Myth",
        "source": "Sprudge",
        "sentiment": "Bullish",
        "confidence": 70.0,
        "tags": [
          "sprudge"
        ]
      },
      {
        "headline": "Build-Outs Of Coffee: Same Time Tomorrow In Harlem, NY",
        "source": "Sprudge",
        "sentiment": "Bullish",
        "confidence": 65.0,
        "tags": [
          "sprudge"
        ]
      },
      {
        "headline": "Update: The Kauai Coffee Company Has Secured Their Land Lease",
        "source": "Sprudge",
        "sentiment": "Bearish",
        "confidence": 75.0,
        "tags": [
          "sprudge"
        ]
      }
    ]
  },
  "robusta_factors": {
    "available": false,
    "reason": "robusta crashed: 'CotWeekly' object has no attribute 'mm_long'"
  },
  "sentiment_calibration": {
    "available": false,
    "warmup": true,
    "reason": "accumulating — 1/8 paired days",
    "n": 1,
    "min_sample": 8,
    "horizon_days": 5
  },
  "open_direction": {
    "available": true,
    "as_of": "2026-07-14",
    "for_session": "2026-07-15",
    "scraped_at": "2026-07-15T05:40:51.743738Z",
    "direction": "Abstain",
    "base_margin": -0.1415814619261737,
    "final_margin": 0.033519962251150476,
    "base_prob": 0.4646636421624934,
    "final_prob": 0.50837920601296,
    "prob_up": 0.50837920601296,
    "prob_down": 0.49162079398703995,
    "regime": {
      "ny_shock": false,
      "vol_regime": "high",
      "vol_percentile": 0.87,
      "harvest_weight": 0.2,
      "harvest_active": false,
      "brent_overnight_pct": null,
      "oil_shock": false
    },
    "expected_gap_pct": 0.016,
    "expected_gap_usd_mt": 0.6,
    "features": [
      {
        "var_name": "days_since_roll",
        "label": "Roll-Cycle Position",
        "raw_value": 29.0,
        "raw_fmt": "day 29",
        "z": 0.89,
        "usd_per_ton": null,
        "phi": 0.14803501670459626,
        "detail": {
          "text": "day 29 of the bi-monthly front-contract cycle — gaps historically tilt down mid-cycle (~day 10), up late-cycle"
        }
      },
      {
        "var_name": "kc_after_rc_diff",
        "label": "NY after RC-Close Move",
        "raw_value": 0.00030590394616103467,
        "raw_fmt": "+0.03%",
        "z": 0.07,
        "usd_per_ton": 1.2,
        "phi": 0.027066407472727937,
        "detail": {
          "text": "KC at RC close (17:30 London) 326.90¢/lb → KC close (18:30) 327.00¢/lb = +2.2 $/t on arabica; +0.03% mapped on robusta ≈ +1.2 $/t"
        }
      }
    ],
    "target": {
      "kind": "overnight_gap",
      "definition": "RC first-bar open ÷ prior 17:30-London close − 1; roll days excluded",
      "abstain_band": 0.1
    },
    "model": {
      "kind": "logistic_regression_l2",
      "active_features": [
        "kc_after_rc_diff",
        "days_since_roll"
      ],
      "n_features": 2,
      "n_train": 1158,
      "test_accuracy": 0.5739514348785872,
      "baseline_accuracy": 0.5353200883002207,
      "edge": 0.03863134657836653,
      "acted_accuracy": 0.6377245508982036,
      "acted_n": 334,
      "abstain_rate": 0.6313465783664459,
      "eval_method": "walk_forward",
      "n_test": 906,
      "mag_mae_pct": 0.3036620975376587,
      "mag_baseline_mae_pct": 0.31073913283082477,
      "mag_skill": 0.022774844058726873,
      "cci_available": false,
      "intraday_source": "barchart_15min",
      "roll_days_excluded": 88
    },
    "track": {
      "live_graded": 5,
      "live_hit_rate": 0.8,
      "rolling_hit_rate": 0.8,
      "rolling_n": 5,
      "cold_streak": false
    }
  }
}